Metadata-Version: 2.1
Name: epubC
Version: 0.2.post1
Summary: .epub file creator
Home-page: https://github.com/firesock/epubc
Author: Awad Mackie
Author-email: firesock.serwalek@gmail.com
License: GPLv3
Keywords: epub,ebook
Platform: UNKNOWN
Classifier: Development Status :: 4 - Beta
Classifier: Environment :: Other Environment
Classifier: Intended Audience :: Developers
Classifier: License :: OSI Approved :: GNU General Public License (GPL)
Classifier: Operating System :: OS Independent
Classifier: Programming Language :: Python
Classifier: Programming Language :: Python :: 3
Classifier: Topic :: Software Development :: Libraries :: Python Modules
